ALU_8_bit.v
module ALU_8_bit(input [7:0]A, B, input [3:0]select, output reg [7:0]ALU_out);

  always @ (*) begin
    case(select)

      4'b0000: ALU_out = A + B;                     // Add A and B
      4'b0001: ALU_out = A - B;                     // Subtract B from A
      4'b0010: ALU_out = A * B;                     // Multiply A and B
      4'b0011: ALU_out = (B != 0) ? A / B : 8'b0;   // Divide A by B, return 0 if B is 0
      4'b0100: ALU_out = A << 1;                    // Logical left shift A by 1
      4'b0101: ALU_out = A >> 1;                    // Logical right shift A by 1
      4'b0110: ALU_out = {A[6:0], A[7]};            // Rotate A left (MSB to LSB)
      4'b0111: ALU_out = {A[0], A[7:1]};            // Rotate A right (LSB to MSB)
      4'b1000: ALU_out = A & B;                     // Bitwise AND of A and B
      4'b1001: ALU_out = A | B;                     // Bitwise OR of A and B
      4'b1010: ALU_out = A ^ B;                     // Bitwise XOR of A and B
      4'b1011: ALU_out = ~(A | B);                  // Bitwise NOR (NOT OR) of A and B
      4'b1100: ALU_out = ~(A & B);                  // Bitwise NAND (NOT AND) of A and B
      4'b1101: ALU_out = ~(A ^ B);                  // Bitwise XNOR (NOT XOR) of A and B
      4'b1110: ALU_out = (A > B) ? 8'd1 : 8'd0;     // Compare A > B, return 1 if true, else 0
      4'b1111: ALU_out = (A == B) ? 8'd1 : 8'd0;    // Compare A == B, return 1 if true, else 0
      default: ALU_out = 8'bx;                      // Default case, undefined output
      
    endcase
  end

endmodule

ALU_8_bit_tb.v
`timescale 1ns/1ps
`include "ALU_8_bit.v"

module ALU_8_bit_tb;
reg [7:0]A,B;
reg [3:0]select;
wire [7:0]ALU_out;

ALU_8_bit uut(A,B,select,ALU_out);

initial begin
$dumpfile("ALU_8_bit_tb.vcd");
$dumpvars(0,ALU_8_bit_tb);

    A = 8'd125;
    B = 8'd5;
    select = 4'b0000; #10; // Test Addition operation
    $display("Add: A = %d, B = %d, Output = %d", A, B, ALU_out);

    select = 4'b0001; #10; // Test Subtraction operation
    $display("Subtract: A = %d, B = %d, Output = %d", A, B, ALU_out);

    select = 4'b0010; #10; // Test Multiplication operation
    $display("Multiply: A = %d, B = %d, Output = %d", A, B, ALU_out);

    select = 4'b0011; #10; // Test Division operation
    $display("Divide: A = %d, B = %d, Output = %d", A, B, ALU_out);

    select = 4'b0100; #10; // Test Logical Left Shift operation
    $display("Left Shift: A = %d, Output = %d", A, ALU_out);

    select = 4'b0101; #10; // Test Logical Right Shift operation
    $display("Right Shift: A = %d, Output = %d", A, ALU_out);

    select = 4'b0110; #10; // Test Rotate Left operation
    $display("Rotate Left: A = %d, Output = %d", A, ALU_out);

    select = 4'b0111; #10; // Test Rotate Right operation
    $display("Rotate Right: A = %d, Output = %d", A, ALU_out);

    select = 4'b1000; #10; // Test Bitwise AND operation
    $display("AND: A = %d, B = %d, Output = %d", A, B, ALU_out);

    select = 4'b1001; #10; // Test Bitwise OR operation
    $display("OR: A = %d, B = %d, Output = %d", A, B, ALU_out);

    select = 4'b1010; #10; // Test Bitwise XOR operation
    $display("XOR: A = %d, B = %d, Output = %d", A, B, ALU_out);

    select = 4'b1011; #10; // Test Bitwise NOR operation
    $display("NOR: A = %d, B = %d, Output = %d", A, B, ALU_out);

    select = 4'b1100; #10; // Test Bitwise NAND operation
    $display("NAND: A = %d, B = %d, Output = %d", A, B, ALU_out);

    select = 4'b1101; #10; // Test Bitwise XNOR operation
    $display("XNOR: A = %d, B = %d, Output = %d", A, B, ALU_out);

    select = 4'b1110; #10; // Test Greater Than operation
    $display("Greater: A = %d, B = %d, Output = %d", A, B, ALU_out);

    select = 4'b1111; #10; // Test Equality operation
    $display("Equality: A = %d, B = %d, Output = %d", A, B, ALU_out);

    // Test division by zero
    A = 8'd10; B = 8'd0; select = 4'b0011; #10;
    $display("Divide by Zero: A = %d, B = %d, Output = %d", A, B, ALU_out);

    // Finish simulation
    $finish;
end

endmodule

ALU_8_bit_tb.vcd
$date
	Sun Jan 26 22:12:43 2025
$end
$version
	Icarus Verilog
$end
$timescale
	1ps
$end
$scope module ALU_8_bit_tb $end
$var wire 8 ! ALU_out [7:0] $end
$var reg 8 " A [7:0] $end
$var reg 8 # B [7:0] $end
$var reg 4 $ select [3:0] $end
$scope module uut $end
$var wire 8 % A [7:0] $end
$var wire 8 & B [7:0] $end
$var wire 4 ' select [3:0] $end
$var reg 8 ( ALU_out [7:0] $end
$upscope $end
$upscope $end
$enddefinitions $end
$comment Show the parameter values. $end
$dumpall
$end
#0
$dumpvars
b10000010 (
b0 '
b101 &
b1111101 %
b0 $
b101 #
b1111101 "
b10000010 !
$end
#10000
b1111000 !
b1111000 (
b1 $
b1 '
#20000
b1110001 !
b1110001 (
b10 $
b10 '
#30000
b11001 !
b11001 (
b11 $
b11 '
#40000
b11111010 !
b11111010 (
b100 $
b100 '
#50000
b111110 !
b111110 (
b101 $
b101 '
#60000
b11111010 !
b11111010 (
b110 $
b110 '
#70000
b10111110 !
b10111110 (
b111 $
b111 '
#80000
b101 !
b101 (
b1000 $
b1000 '
#90000
b1111101 !
b1111101 (
b1001 $
b1001 '
#100000
b1111000 !
b1111000 (
b1010 $
b1010 '
#110000
b10000010 !
b10000010 (
b1011 $
b1011 '
#120000
b11111010 !
b11111010 (
b1100 $
b1100 '
#130000
b10000111 !
b10000111 (
b1101 $
b1101 '
#140000
b1 !
b1 (
b1110 $
b1110 '
#150000
b0 !
b0 (
b1111 $
b1111 '
#160000
b11 $
b11 '
b0 #
b0 &
b1010 "
b1010 %
